{
  "id": 93,
  "title": "Banco del Oeste - Data leak - Undetermined",
  "date": "2014-02-14",
  "country": "USA",
  "region": "Norteamerica",
  "type": "Data leak",
  "actor": "Undetermined",
  "impact": "Sistema o cuenta comprometida en San Francisco",
  "source": "https://www.scmagazine.com/home/opinions/blogs/the-data-breach-blog/hackers-access-bank-of-the-west-job-applicant-data/",
  "summary": "Un número no revelado de personas que solicitaron en línea un puesto en el Bank of the West, con sede en San Francisco, vieron comprometida su información personal (incluidos los números de Seguro Social) después de que una parte no autorizada obtuvo acceso a un sistema de solicitud de empleo.",
  "color": "#3b82f6"
}