{
  "id": 1191,
  "title": "WCHQ 100.9 FM - Manipulación de mensajes - Undetermined",
  "date": "2017-01-23",
  "country": "USA",
  "region": "Norteamerica",
  "type": "Manipulación de mensajes",
  "actor": "Undetermined",
  "impact": "Sistema o cuenta comprometida en Louisville",
  "source": "http://www.ibtimes.co.uk/radio-station-kentucky-hacked-fk-donald-trump-song-played-15-minutes-1602495",
  "summary": "Crescent Hill Radio WCHQ 100.9 FM, una popular estación de radio sin fines de lucro en Louisville, Kentucky, fue hackeada para reproducir una canción anti-Trump durante casi 15 minutos interrumpiendo su programación regular.",
  "color": "#3b82f6"
}