{
  "id": 1281,
  "title": "Alison Brie - Data leak - Undetermined",
  "date": "2017-04-24",
  "country": "USA",
  "region": "Norteamerica",
  "type": "Data leak",
  "actor": "Undetermined",
  "impact": "Filtración de datos en Contin a el",
  "source": "http://www.ibtimes.co.uk/fappening-2-0-leak-celebrity-nudes-continues-alison-brie-targeted-by-hacker-1618338",
  "summary": "Continúa el fappening 2.0: esta vez Alison Brie es la objetivo y tiene algunas imágenes desnudas filtradas en línea.",
  "color": "#ef4444"
}