{
  "id": 1720,
  "title": "Condado de Shiawassee - Data leak - Undetermined",
  "date": "2018-06-02",
  "country": "USA",
  "region": "Norteamerica",
  "type": "Data leak",
  "actor": "Undetermined",
  "impact": "Cuentas comprometidas por phishing en Shiawassee renuncia después de ser atrapado en una estafa de phishing",
  "source": "https://www.databreaches.net/mi-phishing-scam-costs-shiawassee-county-50000/",
  "summary": "El administrador financiero del condado de Shiawassee renuncia después de ser atrapado en una estafa de phishing y transferir por error $ 50,000 a una cuenta bancaria en el extranjero.",
  "color": "#ef4444"
}