{
  "id": 1817,
  "title": "Cocina casera con queso cheddar - Infecci贸n Dispositivos - Undetermined",
  "date": "2018-08-22",
  "country": "USA",
  "region": "Norteamerica",
  "type": "Infecci贸n Dispositivos",
  "actor": "Undetermined",
  "impact": "Filtraci贸n de datos en Cheddar Scratch Kitchen se vieron afectados",
  "source": "https://investor.darden.com/investors/press-releases/press-release-details/2018/Notice-of-Unauthorized-Access-to-Cheddars-Scratch-Kitchen-Guest-Data/default.aspx",
  "summary": "Restaurantes en 23 estados pertenecientes a Cheddar Scratch Kitchen se vieron afectados por un ciberataque que expuso informaci贸n de tarjetas de pago. Se estima que 567,000 datos de tarjetas fueron robados entre el 3 de noviembre de 2017 y el 2 de enero de 2018.",
  "color": "#ef4444"
}