{
  "id": 1983,
  "title": "Cuenta de Twitter de Linda Frum - Manipulación de mensajes - Undetermined",
  "date": "2019-01-06",
  "country": "USA",
  "region": "Norteamerica",
  "type": "Manipulación de mensajes",
  "actor": "Undetermined",
  "impact": "Sistema o cuenta comprometida en Twitter de la senadora conservadora Linda Frum fue hackeada",
  "source": "https://www.databreaches.net/canadian-senators-personal-data-leaked-online-in-apparent-twitter-hack/",
  "summary": "La cuenta de Twitter de la senadora conservadora Linda Frum fue hackeada. Los atacantes compartieron información personal, incluyendo su licencia de conducir, y publicaron tuits racistas.",
  "color": "#3b82f6"
}