{
  "id": 2131,
  "title": "Servicios médicos de Questcare - Data leak - Undetermined",
  "date": "2019-04-12",
  "country": "USA",
  "region": "Norteamerica",
  "type": "Data leak",
  "actor": "Undetermined",
  "impact": "Incidente de seguridad en Questcare Medical Services",
  "source": "https://www.databreaches.net/questcare-medical-services-notifies-north-texas-patients-of-data-security-breach/",
  "summary": "Questcare Medical Services anuncia haber descubierto un incidente de seguridad. El 13 de febrero, un tercero no autorizado obtuvo acceso a la cuenta de correo electrónico de un empleado.",
  "color": "#a78bfa"
}