{
  "id": 2269,
  "title": "Museo de Arte Asiático de San Francisco - Ransomware - Undetermined",
  "date": "2019-07-17",
  "country": "USA",
  "region": "Norteamerica",
  "type": "Ransomware",
  "actor": "Undetermined",
  "impact": "Cifrado por ransomware en Arte Asiático de San Francisco fue víctima de un ataque de ransomware",
  "source": "https://www.databreaches.net/hackers-demanded-ransom-in-may-attack-on-asian-art-museum-computers/",
  "summary": "El Museo de Arte Asiático de San Francisco fue víctima de un ataque de ransomware. El ataque ocurrió en mayo.",
  "color": "#ef4444"
}