{
  "id": 236,
  "title": "Unión Postal Universal - Infección Dispositivos - Undetermined",
  "date": "2014-08-20",
  "country": "USA",
  "region": "Norteamerica",
  "type": "Infección Dispositivos",
  "actor": "Undetermined",
  "impact": "Filtración de datos",
  "source": "https://www.cnet.com/news/the-ups-store-is-hacked-user-data-possibly-compromised/",
  "summary": "UPS admite que 51 de sus tiendas franquiciadas fueron atacadas con malware que puso en riesgo los datos de las tarjetas de crédito y débito de sus clientes del 20 de enero al 11 de agosto.",
  "color": "#ef4444"
}