{
  "id": 2506,
  "title": "Aliado Universal - Ransomware - MAZE",
  "date": "2019-11-21",
  "country": "USA",
  "region": "Norteamerica",
  "type": "Ransomware",
  "actor": "MAZE",
  "impact": "Filtración de datos en Allied Universal",
  "source": "https://www.bleepingcomputer.com/news/security/allied-universal-breached-by-maze-ransomware-stolen-data-leaked/",
  "summary": "Allied Universal se ve afectado por el ransomware Maze y se filtran algunos de los datos robados.",
  "color": "#ef4444"
}