{
  "id": 2985,
  "title": "Intercambio - Ransomware - Undetermined",
  "date": "2020-07-05",
  "country": "USA",
  "region": "Norteamerica",
  "type": "Ransomware",
  "actor": "Undetermined",
  "impact": "Cifrado por ransomware en TI DXC Technology anunció durante el fin de semana un ataque de ransomware a los sistemas de su subsidiaria Xchanging",
  "source": "https://www.bleepingcomputer.com/news/security/ransomware-attack-on-insurance-msp-xchanging-affects-clients/",
  "summary": "El proveedor global de servicios y soluciones de TI DXC Technology anunció durante el fin de semana un ataque de ransomware a los sistemas de su subsidiaria Xchanging.",
  "color": "#ef4444"
}