{
  "id": 3191,
  "title": "Tribunal federal de distrito de Atlanta - Manipulación de mensajes - Undetermined",
  "date": "2020-09-14",
  "country": "USA",
  "region": "Norteamerica",
  "type": "Manipulación de mensajes",
  "actor": "Undetermined",
  "impact": "Incidente de seguridad en Atlanta sobre seguridad electoral fue bombardeada",
  "source": "https://www.theregister.com/2020/09/14/court_hearing_on_election_security/",
  "summary": "Una audiencia judicial de Atlanta sobre seguridad electoral fue bombardeada por Zoom con pornografía, esvásticas e imágenes de los ataques del 11 de septiembre.",
  "color": "#a78bfa"
}