{
  "id": 3321,
  "title": "Servicios de infusión Med-Care, Inc. - Ransomware - INDRIK SPIDER",
  "date": "2020-10-16",
  "country": "USA",
  "region": "Norteamerica",
  "type": "Ransomware",
  "actor": "INDRIK SPIDER",
  "impact": "Cifrado por ransomware en Med-Care Infusion Services Inc",
  "source": "https://www.databreaches.net/wp-content/uploads/Without_Undue_Delay.pdf",
  "summary": "Med-Care Infusion Services, Inc. se suma a la lista de víctimas del ransomware DoppelPaymer.",
  "color": "#ef4444"
}