{
  "id": 3502,
  "title": "Cirujanos Proliance, Inc. - Data leak - Undetermined",
  "date": "2020-12-23",
  "country": "USA",
  "region": "Norteamerica",
  "type": "Data leak",
  "actor": "Undetermined",
  "impact": "Filtración de datos en Proliance",
  "source": "nan",
  "summary": "Proliance Surgeons ha revelado una violación de datos donde es posible que se haya expuesto información de tarjetas de pago de clientes que realizaron pagos en línea en la plataforma de Proliance.",
  "color": "#ef4444"
}