{
  "id": 4697,
  "title": "Suscriptores internacionales Petersen (PIU) - Data leak - Undetermined",
  "date": "2022-07-14",
  "country": "USA",
  "region": "Norteamerica",
  "type": "Data leak",
  "actor": "Undetermined",
  "impact": "Filtración de datos en Petersen International Underwriters PIU",
  "source": "nan",
  "summary": "Petersen International Underwriters (PIU) presenta un aviso oficial de violación de datos a varios gobiernos estatales luego de un incidente en el que una parte no autorizada obtuvo acceso a datos confidenciales de consumidores en la red de la empresa.",
  "color": "#ef4444"
}