{
  "id": 5255,
  "title": "Fideicomiso de miembros de la Cooperativa de Crédito Federal del Suroeste - Data leak - Undetermined",
  "date": "2023-01-20",
  "country": "USA",
  "region": "Norteamerica",
  "type": "Data leak",
  "actor": "Undetermined",
  "impact": "Filtración de datos en Members Trust of the Southwest Federal Credit Union",
  "source": "nan",
  "summary": "Members Trust of the Southwest Federal Credit Union presenta un aviso de violación de datos después de confirmar que una parte no autorizada pudo acceder a la información confidencial de algunos clientes del banco.",
  "color": "#ef4444"
}