{
  "id": 5300,
  "title": "Corporación inmobiliaria Kimco - Data leak - Undetermined",
  "date": "2023-02-08",
  "country": "USA",
  "region": "Norteamerica",
  "type": "Data leak",
  "actor": "Undetermined",
  "impact": "Filtración de datos en Weingarten Realty Investors",
  "source": "nan",
  "summary": "Kimco Realty Corporation presenta un aviso de violación de datos después de que una empresa que Kimco había adquirido, Weingarten Realty Investors, sufriera un ciberataque que resultó en que datos confidenciales de consumidores quedaran expuestos a acceso no autorizado.",
  "color": "#ef4444"
}