{
  "id": 635,
  "title": "Universidad de Servicios Uniformados (https://www.usuhs.mil) - Defacement - Kuroi'SH",
  "date": "2015-10-13",
  "country": "USA",
  "region": "Norteamerica",
  "type": "Defacement",
  "actor": "Kuroi'SH",
  "impact": "Filtración de datos en Servicios Uniformados con sede en Estados Unidos",
  "source": "https://www.hackread.com/uniformed-services-university-domain-hacked/",
  "summary": "Un hacker que utiliza el nombre de usuario en línea Kuroi SH desfigura varios dominios de la Universidad de Servicios Uniformados con sede en Estados Unidos y filtra credenciales de inicio de sesión de 2014 en línea.",
  "color": "#ef4444"
}