{
  "id": 6560,
  "title": "Corporación de aviónica Panasonic - Data leak - Undetermined",
  "date": "2023-12-27",
  "country": "USA",
  "region": "Norteamerica",
  "type": "Data leak",
  "actor": "Undetermined",
  "impact": "Filtración de datos en Panasonic Avionics Corporation un",
  "source": "nan",
  "summary": "Panasonic Avionics Corporation, un proveedor líder de sistemas de comunicaciones y entretenimiento en vuelo, revela una violación de datos que afecta a un número no revelado de personas después de que su red corporativa fuera violada en diciembre de 2022.",
  "color": "#ef4444"
}