{
  "id": 6617,
  "title": "Condado de Fulton - Ransomware - Undetermined",
  "date": "2024-01-29",
  "country": "USA",
  "region": "Norteamerica",
  "type": "Ransomware",
  "actor": "Undetermined",
  "impact": "Cifrado por ransomware en Fulton revela haber experimentado una interrupción generalizada del sistema durante el fin de semana",
  "source": "nan",
  "summary": "El condado de Fulton revela haber experimentado una interrupción generalizada del sistema durante el fin de semana. Un grupo de ransomware se atribuye la responsabilidad del ataque.",
  "color": "#ef4444"
}