{
  "id": 6668,
  "title": "La Mesa - Manipulación de mensajes - Undetermined",
  "date": "2024-03-11",
  "country": "USA",
  "region": "Norteamerica",
  "type": "Manipulación de mensajes",
  "actor": "Undetermined",
  "impact": "Incidente de seguridad en Zoom",
  "source": "nan",
  "summary": "La Mesa suspende temporalmente los comentarios públicos a través de Zoom luego de una serie de discursos de odio antisemitas durante la reunión del Concejo Municipal del mes pasado.",
  "color": "#a78bfa"
}