{
  "id": 6690,
  "title": "Distrito de tasación del condado de Tarrant - Ransomware - Medusa",
  "date": "2024-03-20",
  "country": "USA",
  "region": "Norteamerica",
  "type": "Ransomware",
  "actor": "Medusa",
  "impact": "Cifrado por ransomware en Tasación del Condado de Tarrant sufre un ataque de ransomware",
  "source": "nan",
  "summary": "El Distrito de Tasación del Condado de Tarrant sufre un ataque de ransomware. Aproximadamente dos semanas después, la banda de ransomware Medusa se atribuye la responsabilidad del ataque.",
  "color": "#ef4444"
}