{
  "id": 6904,
  "title": "Access Medicina Deportiva y Ortopedia - Ransomware - INC",
  "date": "2024-10-05",
  "country": "USA",
  "region": "Norteamerica",
  "type": "Ransomware",
  "actor": "INC",
  "impact": "Cifrado por ransomware en Access Sports Medicine Orthopaedics",
  "source": "nan",
  "summary": "Access Sports Medicine & Orthopaedics informa a más de 88.000 personas que su información se vio comprometida como resultado de un ciberataque. El grupo de ransomware Inc Ransom se atribuye la responsabilidad del ataque.",
  "color": "#ef4444"
}