{
  "id": 6918,
  "title": "Artículos deportivos DICK'S - Data leak - Undetermined",
  "date": "2024-08-21",
  "country": "USA",
  "region": "Norteamerica",
  "type": "Data leak",
  "actor": "Undetermined",
  "impact": "Filtración de datos en América",
  "source": "nan",
  "summary": "DICK'S Sporting Goods, la cadena de tiendas minoristas de artículos deportivos más grande de los Estados Unidos de América, revela que información confidencial fue expuesta en un ciberataque.",
  "color": "#ef4444"
}