{
  "id": 7003,
  "title": "ZAGG Inc. - Data leak - Undetermined",
  "date": "2024-10-26",
  "country": "USA",
  "region": "Norteamerica",
  "type": "Data leak",
  "actor": "Undetermined",
  "impact": "Filtración de datos en ZAGG",
  "source": "nan",
  "summary": "ZAGG informa a sus clientes que los datos de sus tarjetas de crédito han sido expuestos a personas no autorizadas después de que piratas informáticos comprometieran una aplicación de terceros proporcionada por el proveedor de comercio electrónico de la compañía, BigCommerce.",
  "color": "#ef4444"
}