{
  "id": 703,
  "title": "Abby Lee Miller - Data leak - Undetermined",
  "date": "2015-12-29",
  "country": "USA",
  "region": "Norteamerica",
  "type": "Data leak",
  "actor": "Undetermined",
  "impact": "Incidente de seguridad en Dance Moms",
  "source": "https://www.tmz.com/2015/12/29/dance-moms-hackers-investigation/",
  "summary": "Varios miembros del elenco de Dance Moms, incluidos Abby Lee Miller, Mackenzie Ziegler y otros, tienen sus números de teléfono y otra información del elenco publicados en las redes sociales por un pirata informático desconocido.",
  "color": "#a78bfa"
}