{
  "id": 7806,
  "title": "Spa termal - Data leak - Undetermined",
  "date": "2023-02-28",
  "country": "Canada",
  "region": "Norteamerica",
  "type": "Data leak",
  "actor": "Undetermined",
  "impact": "Sistema o cuenta comprometida en Thermea Spa entre principios de noviembre",
  "source": "nan",
  "summary": "A los clientes que compraron certificados de regalo de Thermea Spa entre principios de noviembre y fines de febrero se les informa en un correo electrónico que la información de su tarjeta de crédito puede haber sido comprometida, junto con sus nombres completos, números de teléfono y direcciones de correo electrónico y postales.",
  "color": "#3b82f6"
}