{
  "id": 7859,
  "title": "Recursos de Clearview - Ciberataque - Undetermined",
  "date": "2023-12-06",
  "country": "Canada",
  "region": "Norteamerica",
  "type": "Ciberataque",
  "actor": "Undetermined",
  "impact": "Incidente de seguridad en Clearview Resources un",
  "source": "nan",
  "summary": "Clearview Resources, un productor canadiense de energía, revela detalles sobre un ciberataque que le provocó a la empresa una pérdida financiera de 1,5 millones de dólares.",
  "color": "#a78bfa"
}