{
  "id": 7898,
  "title": "Gobierno del Estado de São Paulo - Data leak - Anonymous",
  "date": "2014-01-28",
  "country": "Brasil",
  "region": "Latinoamerica",
  "type": "Data leak",
  "actor": "Anonymous",
  "impact": "Sistema o cuenta comprometida en saopaulo.sp.gov.br",
  "source": "nan",
  "summary": "Un hacker afiliado a Anonymous hackea la cuenta de correo electrónico oficial del departamento de prensa y comunicación del gobierno del estado de Sao Paulo (saopaulo.sp.gov.br/).",
  "color": "#3b82f6"
}